magcluster/__init__.py
magcluster/args.py
magcluster/batch_proc.py
magcluster/capture_args.py
magcluster/change_data.py
magcluster/controller.py
magcluster/maga.py
magcluster/magm.py
magcluster/magsc_new.py
magcluster/data/Magnetosome_protein_data.fasta
magcluster/data/__init__.py
magcluster-0.2.5.dist-info/LICENSE.txt
magcluster-0.2.5.dist-info/METADATA
magcluster-0.2.5.dist-info/WHEEL
magcluster-0.2.5.dist-info/entry_points.txt
magcluster-0.2.5.dist-info/top_level.txt
magcluster-0.2.5.dist-info/RECORD
