Metadata-Version: 2.1
Name: magcluster
Version: 0.2.5
Summary: Magnetosome Gene Clusters Analyzer
Home-page: https://github.com/RunJiaJi/magcluster
Author: Runjia Ji
Author-email: jirunjia@gmail.com
Classifier: Programming Language :: Python :: 3.0
Classifier: Programming Language :: Python :: 3.6
Classifier: Programming Language :: Python :: 3.7
Classifier: License :: OSI Approved :: GNU General Public License v2 or later (GPLv2+)
Classifier: Operating System :: POSIX :: Linux
License-File: LICENSE.txt
Requires-Dist: clinker
Requires-Dist: pandas
